uquake/__init__.py
uquake/nlloc/__init__.py
uquake/nlloc/api/__init__.py
uquake/nlloc/api/grids/__init__.py
uquake/nlloc/api/grids/database.py
uquake/nlloc/api/grids/main.py
uquake/nlloc/api/grids/settings.py
uquake/nlloc/api/grids/test.http
uquake/nlloc/api/nlloc/__init__.py
uquake/nlloc/api/nlloc/main.py
uquake/nlloc/api/nlloc/settings.py
uquake/nlloc/nlloc.py
uquake/nlloc/settings.py
uquake/nlloc/settings.toml
uquake.nlloc-0.2.4.dist-info/entry_points.txt
uquake.nlloc-0.2.4.dist-info/LICENSE
uquake.nlloc-0.2.4.dist-info/WHEEL
uquake.nlloc-0.2.4.dist-info/METADATA
uquake.nlloc-0.2.4.dist-info/RECORD
