Metadata-Version: 2.1
Name: uquake.nlloc
Version: 0.2.4
Summary: wrapper around A. Lomax NLLoc
License: GNU GENERAL PUBLIC LICENSE Version 3
Author: jpmercier
Author-email: jpmercier01@gmail.com
Requires-Python: >=3.8,<4.0
Classifier: License :: Other/Proprietary License
Classifier: Programming Language :: Python :: 3
Classifier: Programming Language :: Python :: 3.8
Classifier: Programming Language :: Python :: 3.9
Requires-Dist: Cython (>=0.29.21,<0.30.0)
Requires-Dist: dvc (>=1.11.15,<2.0.0)
Requires-Dist: dynaconf (>=3.1.3,<4.0.0)
Requires-Dist: fastapi (>=0.63.0,<0.64.0)
Requires-Dist: h5py (>=3.2.1,<4.0.0)
Requires-Dist: ipdb (>=0.13.6,<0.14.0)
Requires-Dist: ipython (>=7.20.0,<8.0.0)
Requires-Dist: jedi (>=0.17.2,<0.18.0)
Requires-Dist: matplotlib (>=3.3.4,<4.0.0)
Requires-Dist: obspy (>=1.2.2,<2.0.0)
Requires-Dist: phonenumbers (==8.12.18)
Requires-Dist: pytest (>=6.2.2,<7.0.0)
Requires-Dist: scikit-fmm (>=2021.2.2,<2022.0.0)
Requires-Dist: setuptools_cpp (>=0.1.0,<0.2.0)
Requires-Dist: uvicorn (>=0.13.4,<0.14.0)
